ocfinance/__init__.py
ocfinance/download.py
ocfinance/scraper/__init__.py
ocfinance/scraper/bitbo.py
ocfinance/scraper/bitcoinmagazinepro.py
ocfinance/scraper/blockchain.py
ocfinance/scraper/chainexposed.py
ocfinance/scraper/checkonchain.py
ocfinance/scraper/cryptoquant.py
ocfinance/scraper/utils.py
ocfinance/scraper/woocharts.py
ocfinance-0.0.12.dist-info/licenses/LICENSE
ocfinance-0.0.12.dist-info/METADATA
ocfinance-0.0.12.dist-info/WHEEL
ocfinance-0.0.12.dist-info/top_level.txt
ocfinance-0.0.12.dist-info/RECORD
