Metadata-Version: 2.4
Name: ocfinance
Version: 0.0.12
Summary: Download on-chain data for bitcoin (works for cryptoquant)
Author-email: Dhruvan Gnanadhandayuthapani <dhruvan2006@gmail.com>
License-Expression: MIT
Project-URL: Homepage, https://github.com/dhruvan2006/ocfinance
Project-URL: Documentation, https://ocfinance.readthedocs.io/
Project-URL: PyPI, https://pypi.org/project/ocfinance/
Project-URL: Issues, https://github.com/dhruvan2006/ocfinance/issues
Classifier: Programming Language :: Python :: 3
Classifier: Development Status :: 5 - Production/Stable
Classifier: Operating System :: OS Independent
Requires-Python: >=3.8
License-File: LICENSE
Requires-Dist: requests
Requires-Dist: pandas
Requires-Dist: beautifulsoup4
Requires-Dist: seleniumbase
Requires-Dist: selenium
Requires-Dist: selenium-wire
Requires-Dist: blinker==1.7.0
Dynamic: license-file
